Metadata-Version: 1.0
Name: logtrigger
Version: 1.0
Summary: Trigger tasks by monitoring logs
Home-page: https://github.com/ipconfiger/logtrigger
Author: Alexander.Lee
Author-email: superpowerlee@gmail.com
License: UNKNOWN
Platform: UNKNOWN
